KnowBe4Wrapper/KnowBe4.py
KnowBe4Wrapper/__init__.py
KnowBe4Wrapper-1.0.0.dist-info/METADATA
KnowBe4Wrapper-1.0.0.dist-info/WHEEL
KnowBe4Wrapper-1.0.0.dist-info/top_level.txt
KnowBe4Wrapper-1.0.0.dist-info/RECORD
