Metadata-Version: 2.1
Name: KnowBe4Wrapper
Version: 1.0.0
Summary: KnowBe4 API Python Wrapper
Home-page: UNKNOWN
Author: Chase Geis
Author-email: <Chasegeis@gmail.com>
License: UNKNOWN
Keywords: python,KnowBe4,KnowBe4 API,API,KnowBe4 Wrapper,KnowBe4 Python Wrapper
Platform: UNKNOWN
Classifier: Development Status :: 3 - Alpha
Classifier: Intended Audience :: Education
Classifier: Programming Language :: Python :: 2
Classifier: Programming Language :: Python :: 3
Classifier: Operating System :: MacOS :: MacOS X
Classifier: Operating System :: Microsoft :: Windows
Requires-Dist: requests
